orphanet_explorer/__init__.py
orphanet_explorer/exceptions.py
orphanet_explorer/orphanet_explorer.py
orphanet_explorer/test.ipynb
orphanet_explorer/utils.py
orphanet_explorer/.ipynb_checkpoints/__init__-checkpoint.py
orphanet_explorer/.ipynb_checkpoints/exceptions-checkpoint.py
orphanet_explorer/.ipynb_checkpoints/orphanet_explorer-checkpoint.py
orphanet_explorer/.ipynb_checkpoints/test-checkpoint.ipynb
orphanet_explorer/.ipynb_checkpoints/utils-checkpoint.py
orphanet_explorer-0.2.0.dist-info/METADATA
orphanet_explorer-0.2.0.dist-info/WHEEL
orphanet_explorer-0.2.0.dist-info/licenses/LICENSE
orphanet_explorer-0.2.0.dist-info/RECORD
