Metadata-Version: 2.4
Name: orphanet_explorer
Version: 0.2.0
Summary: A package to extract and merge Orphanet data from XML files.
Project-URL: Homepage, https://github.com/atinak/orphanet_explorer
Project-URL: Bug Tracker, https://github.com/atinak/orphanet_explorer/issues
Author-email: "A. Tinakoua" <a.tinakoua@gmail.com>
License: MIT License
License-File: LICENSE
Classifier: License :: OSI Approved :: MIT License
Classifier: Operating System :: OS Independent
Classifier: Programming Language :: Python :: 3
Classifier: Topic :: Scientific/Engineering :: Bio-Informatics
Requires-Python: >=3.7
Requires-Dist: lxml
Requires-Dist: pandas
